compas_wood/__init__.py
compas_wood/__main__.py
compas_wood/conversions_compas.py
compas_wood/conversions_rhino.py
compas_wood/data_sets_plates.py
compas_wood/binding/__init__.py
compas_wood/binding/binding_beam_volumes.py
compas_wood/binding/binding_closed_mesh_from_polylines.py
compas_wood/binding/binding_get_connection_zones.py
compas_wood/binding/binding_globals.py
compas_wood/binding/binding_joints.py
compas_wood/binding/binding_mesh_boolean_difference_from_polylines.py
compas_wood/binding/binding_read_xml_polylines.py
compas_wood/binding/binding_read_xml_polylines_and_properties.py
compas_wood/binding/binding_rtree.py
compas_wood/binding/binding_skeleton.py
compas_wood/binding/binding_test.py
compas_wood/binding_rhino/__init__.py
compas_wood/binding_rhino/binding_skeleton.py
compas_wood/binding_rhino/binding_test.py
compas_wood/datasets/in_beam_node_0.xml
compas_wood/datasets/out.xml
compas_wood/datasets/type_beams_name_phanomema_node.xml
compas_wood/datasets/type_plates_name_cross_and_sides_corner.xml
compas_wood/datasets/type_plates_name_cross_brg_slab_0.xml
compas_wood/datasets/type_plates_name_cross_brussels_sports_tower.xml
compas_wood/datasets/type_plates_name_cross_corners.xml
compas_wood/datasets/type_plates_name_cross_ibois_pavilion.xml
compas_wood/datasets/type_plates_name_cross_square_reciprocal_iseya.xml
compas_wood/datasets/type_plates_name_cross_square_reciprocal_two_sides.xml
compas_wood/datasets/type_plates_name_cross_vda_corner.xml
compas_wood/datasets/type_plates_name_cross_vda_hexshell.xml
compas_wood/datasets/type_plates_name_cross_vda_hexshell_reciprocal.xml
compas_wood/datasets/type_plates_name_cross_vda_shell.xml
compas_wood/datasets/type_plates_name_cross_vda_single_arch.xml
compas_wood/datasets/type_plates_name_hex_block_rossiniere.xml
compas_wood/datasets/type_plates_name_hexbox_and_corner.xml
compas_wood/datasets/type_plates_name_joint_linking_vidychapel_corner.xml
compas_wood-2.4.0.dist-info/AUTHORS.md
compas_wood-2.4.0.dist-info/LICENSE
compas_wood-2.4.0.dist-info/METADATA
compas_wood-2.4.0.dist-info/WHEEL
compas_wood-2.4.0.dist-info/top_level.txt
compas_wood-2.4.0.dist-info/RECORD
